CHANGES.rst
LICENSE
MANIFEST.in
README.rst
setup.py
django_cloneable/__init__.py
django_cloneable/models.py
django_cloneable.egg-info/PKG-INFO
django_cloneable.egg-info/SOURCES.txt
django_cloneable.egg-info/dependency_links.txt
django_cloneable.egg-info/not-zip-safe
django_cloneable.egg-info/top_level.txt
tests/__init__.py
tests/models.py
tests/requirements.txt
tests/settings.py
tests/test_cloneable.py
tests/test_imports.py