Metadata-Version: 1.1
Name: django-cloneable
Version: 0.1.0
Summary: Let's you clone a Django model instance including many to many fields
Home-page: https://github.com/team23/django_cloneable
Author: David Danier
Author-email: david.danier@team23.de
License: BSD licence, see LICENSE file
Platform: UNKNOWN
Classifier: Development Status :: 4 - Beta
Classifier: Environment :: Web Environment
Classifier: Framework :: Django
Classifier: Framework :: Django :: 1.8
Classifier: Framework :: Django :: 1.9
Classifier: Intended Audience :: Developers
Classifier: License :: OSI Approved :: BSD License
Classifier: Natural Language :: English
Classifier: Programming Language :: Python
Classifier: Programming Language :: Python :: 2
Classifier: Programming Language :: Python :: 2.7
Classifier: Programming Language :: Python :: 3.5
